provides/__init__.py
provides/errors.py
provides-0.0.1.dist-info/LICENSE
provides-0.0.1.dist-info/WHEEL
provides-0.0.1.dist-info/METADATA
provides-0.0.1.dist-info/RECORD
